essos/__init__.py
essos/__main__.py
essos/background_species.py
essos/coils.py
essos/constants.py
essos/dynamics.py
essos/electric_field.py
essos/fields.py
essos/multiobjectiveoptimizer.py
essos/objective_functions.py
essos/optimization.py
essos/plot.py
essos/surfaces.py
essos/util.py
essos/version.py
essos-0.16.dist-info/licenses/LICENSE
essos-0.16.dist-info/METADATA
essos-0.16.dist-info/WHEEL
essos-0.16.dist-info/entry_points.txt
essos-0.16.dist-info/top_level.txt
essos-0.16.dist-info/RECORD
