Metadata-Version: 2.4
Name: essos
Version: 0.16
Summary: ESSOS: e-Stellarator Simulation and Optimization Suite
Author-email: "UWPlasma, UW-Madison group" <rogerio.jorge@wisc.edu>
License: MIT License
Project-URL: Homepage, https://github.com/uwplasma/ESSOS
Keywords: Plasma,Physics,Simulation,JAX
Classifier: Development Status :: 3 - Alpha
Classifier: Operating System :: OS Independent
Classifier: License :: OSI Approved :: MIT License
Classifier: Programming Language :: Python :: 3
Requires-Python: >=3.10
License-File: LICENSE
Requires-Dist: jax
Requires-Dist: jaxlib
Requires-Dist: tqdm
Requires-Dist: matplotlib
Requires-Dist: diffrax
Requires-Dist: optax
Requires-Dist: scipy
Requires-Dist: jaxkd
Requires-Dist: netcdf4
Dynamic: license-file
